dash_blueprint_components/Alert.py
dash_blueprint_components/AnchorButton.py
dash_blueprint_components/Breadcrumb.py
dash_blueprint_components/Button.py
dash_blueprint_components/ButtonGroup.py
dash_blueprint_components/Callout.py
dash_blueprint_components/Card.py
dash_blueprint_components/CardList.py
dash_blueprint_components/Checkbox.py
dash_blueprint_components/CheckboxCard.py
dash_blueprint_components/Collapse.py
dash_blueprint_components/CompoundTag.py
dash_blueprint_components/ContextMenu.py
dash_blueprint_components/ControlGroup.py
dash_blueprint_components/DateInput.py
dash_blueprint_components/DatePicker.py
dash_blueprint_components/DateRangeInput.py
dash_blueprint_components/DateRangePicker.py
dash_blueprint_components/Dialog.py
dash_blueprint_components/DialogBody.py
dash_blueprint_components/DialogFooter.py
dash_blueprint_components/DialogStep.py
dash_blueprint_components/Divider.py
dash_blueprint_components/Drawer.py
dash_blueprint_components/EditableText.py
dash_blueprint_components/EntityTitle.py
dash_blueprint_components/FileInput.py
dash_blueprint_components/FormGroup.py
dash_blueprint_components/HTMLSelect.py
dash_blueprint_components/Handle.py
dash_blueprint_components/Icon.py
dash_blueprint_components/InputGroup.py
dash_blueprint_components/Menu.py
dash_blueprint_components/MenuDivider.py
dash_blueprint_components/MenuItem.py
dash_blueprint_components/MultiSelect.py
dash_blueprint_components/MultiSlider.py
dash_blueprint_components/MultistepDialog.py
dash_blueprint_components/NavMenu.py
dash_blueprint_components/Navbar.py
dash_blueprint_components/NavbarDivider.py
dash_blueprint_components/NavbarGroup.py
dash_blueprint_components/NavbarHeading.py
dash_blueprint_components/NumericInput.py
dash_blueprint_components/Omnibar.py
dash_blueprint_components/OverlayToaster.py
dash_blueprint_components/Popover.py
dash_blueprint_components/ProgressBar.py
dash_blueprint_components/Radio.py
dash_blueprint_components/RadioCard.py
dash_blueprint_components-0.3.0.dist-info/licenses/LICENSE
dash_blueprint_components-0.3.0.dist-info/METADATA
dash_blueprint_components-0.3.0.dist-info/WHEEL
dash_blueprint_components-0.3.0.dist-info/top_level.txt
dash_blueprint_components-0.3.0.dist-info/RECORD
