Metadata-Version: 2.4
Name: dash_blueprint_components
Version: 0.3.0
Summary: Dash plotly porting of BlueprintJS
Author: Stefano Fanizzi <ste.fanizzi@outlook.com>
License: MIT
Project-URL: Bug Reports, https://github.com/STEdyd666/dash-blueprint-components/issues
Project-URL: Source, https://github.com/STEdyd666/dash-blueprint-components
Project-URL: Documentation, https://dash-blueprint-components.com/blueprint
Classifier: Framework :: Dash
License-File: LICENSE
Dynamic: author
Dynamic: classifier
Dynamic: description
Dynamic: description-content-type
Dynamic: license
Dynamic: license-file
Dynamic: project-url
Dynamic: summary
